narou_api/__init__.py
narou_api/__main__.py
narou_api/__pycache__/__init__.cpython-38.pyc
narou_api-1.0.1.dist-info/LICENSE
narou_api-1.0.1.dist-info/METADATA
narou_api-1.0.1.dist-info/WHEEL
narou_api-1.0.1.dist-info/entry_points.txt
narou_api-1.0.1.dist-info/top_level.txt
narou_api-1.0.1.dist-info/RECORD
